cortex/__init__.py
cortex/_convex_async.py
cortex/_utils.py
cortex/client.py
cortex/errors.py
cortex/py.typed
cortex/types.py
cortex/a2a/__init__.py
cortex/a2a/validators.py
cortex/agents/__init__.py
cortex/agents/validators.py
cortex/auth/__init__.py
cortex/auth/context.py
cortex/auth/validators.py
cortex/contexts/__init__.py
cortex/contexts/validators.py
cortex/conversations/__init__.py
cortex/conversations/validators.py
cortex/facts/__init__.py
cortex/facts/belief_revision.py
cortex/facts/conflict_prompts.py
cortex/facts/deduplication.py
cortex/facts/history.py
cortex/facts/slot_matching.py
cortex/facts/validators.py
cortex/governance/__init__.py
cortex/governance/validators.py
cortex/graph/__init__.py
cortex/graph/batch_sync.py
cortex/graph/errors.py
cortex/graph/orphan_detection.py
cortex/graph/schema.py
cortex/graph/worker.py
cortex/graph/adapters/__init__.py
cortex/graph/adapters/cypher.py
cortex/graph/schema/__init__.py
cortex/graph/schema/init_schema.py
cortex/graph/sync/__init__.py
cortex/graph/sync/orphan_detection.py
cortex/graph/worker/__init__.py
cortex/graph/worker/sync_worker.py
cortex/immutable/__init__.py
cortex/immutable/validators.py
cortex/llm/__init__.py
cortex/memory/__init__.py
cortex/memory/stream_utils.py
cortex/memory/streaming_types.py
cortex/memory/validators.py
cortex/memory/recall/__init__.py
cortex/memory/recall/graph_enhancement.py
cortex/memory/recall/result_processor.py
cortex/memory/streaming/__init__.py
cortex/memory/streaming/adaptive_processor.py
cortex/memory/streaming/chunking_strategies.py
cortex/memory/streaming/error_recovery.py
cortex/memory/streaming/fact_extractor.py
cortex/memory/streaming/progressive_graph_sync.py
cortex/memory/streaming/progressive_storage_handler.py
cortex/memory/streaming/stream_metrics.py
cortex/memory/streaming/stream_processor.py
cortex/memory_spaces/__init__.py
cortex/memory_spaces/validators.py
cortex/mutable/__init__.py
cortex/mutable/validators.py
cortex/resilience/__init__.py
cortex_memory-0.27.0.dist-info/licenses/LICENSE.md
cortex_memory-0.27.0.dist-info/METADATA
cortex_memory-0.27.0.dist-info/WHEEL
cortex_memory-0.27.0.dist-info/top_level.txt
cortex_memory-0.27.0.dist-info/RECORD
