Metadata-Version: 2.4
Name: cortex-memory
Version: 0.27.0
Summary: AI agent memory SDK built on Convex - ACID storage, vector search, and conversation management
Home-page: https://github.com/SaintNick1214/Project-Cortex
Author: Saint Nick LLC
Author-email: Saint Nick LLC <support@cortexmemory.dev>
License: # Functional Source License, Version 1.1, Apache 2.0 Future License
Project-URL: Homepage, https://github.com/SaintNick1214/Project-Cortex
Project-URL: Documentation, https://github.com/SaintNick1214/Project-Cortex/tree/main/Documentation
Project-URL: Repository, https://github.com/SaintNick1214/Project-Cortex
Project-URL: Issues, https://github.com/SaintNick1214/Project-Cortex/issues
Keywords: ai,agents,memory,convex,sdk,python,conversations,vector-search,llm,chatbot,knowledge-graph,facts,hive-mode,memory-spaces,workflow-coordination,multi-agent,infinite-context
Classifier: Development Status :: 4 - Beta
Classifier: Intended Audience :: Developers
Classifier: Programming Language :: Python :: 3
Classifier: Programming Language :: Python :: 3.10
Classifier: Programming Language :: Python :: 3.11
Classifier: Programming Language :: Python :: 3.12
Classifier: Programming Language :: Python :: 3.13
Classifier: Programming Language :: Python :: 3.14
Classifier: Topic :: Software Development :: Libraries :: Python Modules
Classifier: Topic :: Scientific/Engineering :: Artificial Intelligence
Classifier: Framework :: AsyncIO
Classifier: Typing :: Typed
Requires-Python: >=3.10
License-File: LICENSE.md
Requires-Dist: convex>=0.5.0
Requires-Dist: pydantic>=2.4.0
Requires-Dist: typing-extensions>=4.0
Provides-Extra: graph
Requires-Dist: neo4j>=5.0; extra == "graph"
Provides-Extra: a2a
Requires-Dist: redis>=5.0; extra == "a2a"
Provides-Extra: llm
Requires-Dist: openai>=1.0; extra == "llm"
Requires-Dist: anthropic>=0.30.0; extra == "llm"
Provides-Extra: openai
Requires-Dist: openai>=1.0; extra == "openai"
Provides-Extra: anthropic
Requires-Dist: anthropic>=0.30.0; extra == "anthropic"
Provides-Extra: all
Requires-Dist: neo4j>=5.0; extra == "all"
Requires-Dist: redis>=5.0; extra == "all"
Requires-Dist: openai>=1.0; extra == "all"
Requires-Dist: anthropic>=0.30.0; extra == "all"
Provides-Extra: dev
Requires-Dist: pytest>=8.0; extra == "dev"
Requires-Dist: pytest-asyncio>=0.23; extra == "dev"
Requires-Dist: pytest-xdist>=3.0; extra == "dev"
Requires-Dist: pytest-cov>=4.0; extra == "dev"
Requires-Dist: pytest-timeout>=2.0; extra == "dev"
Requires-Dist: black>=24.3.0; extra == "dev"
Requires-Dist: mypy>=1.0; extra == "dev"
Requires-Dist: ruff>=0.1; extra == "dev"
Requires-Dist: sphinx>=7.0; extra == "dev"
Requires-Dist: sphinx-rtd-theme>=2.0; extra == "dev"
Requires-Dist: openai>=1.0; extra == "dev"
Requires-Dist: anthropic>=0.30.0; extra == "dev"
Dynamic: author
Dynamic: home-page
Dynamic: license-file
Dynamic: requires-python
